{"title":"Blanchard's Winter","markdown":{"yaml":{"title":"Blanchard's Winter","editor":{"markdown":{"wrap":"sentence"}}},"headingText":"Military plans","containsRefs":false,"markdown":"\n\n__UNDER CONSTRUCTION__\n\n[Blanchard the Hyperborean](/Proteus/Blanchard_the_hyperborean.qmd) is holding New York ransom for 1 Billion dollars.\nHe is utilising a weather machine to cause an unending blizzard in NY.\nIf he doesn't get his money on midnight of the Winter solstice he will freeze the city and it inhabitants.\n\nBlanchard's fortress is on an Ice berg off Newfoundland, Canada.\nThe iceberg is secretly above the sunken Titanic (found on 1st of September 1985 in the real world).\nBlanchard and his weather machine are actually in the Titanic, rebuilt as an underwater sea base.\n\nHis iceberg is protected by extreme cold weather.\nThick ice crystals in the frozen sky disable missiles and planes.\nMind controlled cyborg orcas and thick ice protect from sea invasions.\n\n\nThe USA and [ERA](/History/ERA.qmd) plan to assault the Ice fortress.\nWhilst the main force is distracting the defences this will allow an elite force, including the FIST team, to invade.\n\nFIST will be debriefed on a USA Aircraft carrier.\nThey will be informed of the information in the Sea invasion section.\nThis includes the formation used and what enemies will be present.\nThey will then be tasked with destroying one of the weather spires on the iceberg.\nThis will allow some reinforcement to arrive and also allow the use of Rods from God.\nThey know the main ice fortress is in the centre but do not know what is in it.\n\nEach FIST merc will be provided with the following gear to use during the mission:\n\n- Heated aqua combat suits (1 ARMOR), goes on top of their ground clothing\n- Waterproof backpack allowing storage of 4 items\n- Harpoon gun (1D6+1 DAMAGE)\n\nAdditionally, the FIST team will be provided with 1:\n\n- Rod from God laser targetter (3D6+3, ANTI-MATERIAL), calls down a rod from god. Only works in the air.\n\nWhilst on board FIST can also:\n\n- Enquire about more more intel\n- Give their [CYBORG COLOSSAL SQUIDS](/History/ERA_military.qmd#cyborg_colossal_squid) their 10 word directive.\n- Talk to the leaders of Whale-1 & Whale-2\n\n\n## Sea invasion\n\nThe sea is an uninviting abyss.\nEven with the suits the mercs are frozen to the bone, but they are dry.\nEnemies appear out of nowhere for humans.\nThankfully FIST's steeds do not have this issue.\n\nThe sea invasion consists of an escort mission to the iceberg.\nThey will be attacked by mind controlled Cyborg Orcas and their wranglers.\nReaching the Iceberg is the path to victory.\n\n### Frontal forces\n\nDuring the sea invasion FIST's team will trail behind 2 military groups in the water, Whale-1 & Whale-2.\nThese military groups each consist of 6 marines riding [CYBORG DOLPHINS](/History/USA_military.qmd#cyborg_dolphin), 2 [CYBORG COLOSSAL SQUIDS](/History/ERA_military.qmd#cyborg_colossal_squid), and a [HUMPBACK WHALE SUBMERSIBLE](/History/USA_military.qmd#humpback_sub).\nDo not control directly control these units.\nRather, during the sea invasion, narrate their actions every so often making them succeed and fail in line with the rolls of the FIST characters.\nFor example, if a FIST character rolls a success you can also narrate how the front teams are holding off and killing their enemies.\nIf a FIST character rolls a failure you can narrate and mark the death of members in the front teams.\nOn partial successes the front team may take some losses but also kill some enemies.\n\n### FIST's team\n\nFISTS crew will consists of:\n\n- The FIST mercs\n- A number of [CYBORG DOLPHINS](/History/USA_military.qmd#cyborg_dolphin) equal to 1.5X the number of FIST mercs (rounded down)\n- 2 [CYBORG COLOSSAL SQUIDS](/History/ERA_military.qmd#cyborg_colossal_squid)\n- A [HUMPBACK WHALE SUBMERSIBLE](/History/USA_military.qmd#humpback_sub)\n\n### Blanchard's sea forces\n\nWhilst underwater and approaching the Iceberg the Whale teams will be attacked.\nFIST's team will have to fend off a pod of 6 [CYBORG ORCAS](/Proteus/Blanchard_the_hyperborean.qmd#cyborg_orca) and their [ORCA WRANGLER](/Proteus/Blanchard_the_hyperborean.qmd#orca_wrangler).\nThe frontal forces will be attacked by the same enemies but in larger numbers.\n\n### Victory\n\nThe main goal of FIST is to protect the [HUMPBACK WHALE SUBMERSIBLE](/History/USA_military.qmd#humpback_sub) to the iceberg.\nIt will take 3-6 turns, or however else you measure combat, to reach the iceberg.\nIf FIST are doing well in combat it will take less time than if they are performing poorly.\n\nOnce the Iceberg has been reached the [CYBORG DOLPHINS](/History/USA_military.qmd#cyborg_dolphin) and [HUMPBACK WHALE SUBMERSIBLE](/History/USA_military.qmd#humpback_sub) can climb onto it.\n\n## Ground invasion\n\nEven the dolphins and whales are happy to be out of the sea due to the relative warmth of 0°C air.\nHowever, the dark blue has been replaced by the bright white.\nA flat iceberg surface and still white air disguise the horizon.\n\nThis vision of infinity is slightly broken by the barely visible Ice structures in the distance.\nAs FIST sets up the silence is broken by the sound of fast approaching heavy footsteps.\n\n### Landfall\n\nOnce on land the surviving [HUMPBACK WHALE SUBMERSIBLES](/History/USA_military.qmd#humpback_sub) will deploy into [HUMPBACK WHALE WEAPONS PLATFORM](/History/USA_military.qmd#humpback_plat).\nThis will take a minute or 2 requiring FIST to protect the whale.\nThe mercs will need to remove their Heated aqua combat suits and unpack their gear from their bags.\nIf the other whale teams successfully made it to land this will give more time for FIST's team to set-up before combatants engage them.\n\nThe vanguard of Blanchard's forces will consist of 1D6 [CYBORG POLAR BEAR](#cyborg_polar_bear) with one [POLAR BEAR RIDER](/Proteus/Blanchard_the_hyperborean.qmd#cyborg_polar_bear_rider) each.\n\n### Weather Spire attack\n\nAfter set-up and taking care of the vanguard FIST will need to destroy a weather spire.\nThis will clear a patch of the frozen sky to allow reinforcements to drop in.\nAdditionally, FIST will then be able to use their Rod from God laser targetter.\n\nClose to the weather spire, FIST's team will encounter 8 - X (X is equal to 2 times the number of other whale teams that survived) [CYBORG POLAR BEARS](/Proteus/Blanchard_the_hyperborean.qmd#cyborg_polar_bear) with one [POLAR BEAR RIDER](/Proteus/Blanchard_the_hyperborean.qmd#cyborg_polar_bear_rider) each.\n\nThe weather spire is closely surrounded by 4 defence spires, 1 at each compass point. Each defence spire has 3 [BLANCHARD RIFLEMEN](/Proteus/Blanchard_the_hyperborean.qmd#Blanchard_rifleman) stationed on top of them.\n\n__Weather Spire__ (25HP): A tall tower of ice. At the top of the spire ice is spouting out forming the above frozen sky.\n\n### Weather Spire destruction\n\nOnce the weather spire is deactivated mechas will drop in from the mooners.\nThey will obliterate enemies allowing FIST a clear path to Blanchard's Ice Dome.\n\n## Ice Dome\n\nOnly contains an elevator, a great place for FIST to take a break (rendezvous).\nThe elevator leads down into the sea, it takes a long time going all the way to the Titanic on the sea floor.\n\n## Titanic base\n\nBlanchard and his weather machine are here. He has patch up the Titanic with Ice.\n\n\n\n\n\n\n\n\n\n\n","srcMarkdownNoYaml":"\n\n__UNDER CONSTRUCTION__\n\n[Blanchard the Hyperborean](/Proteus/Blanchard_the_hyperborean.qmd) is holding New York ransom for 1 Billion dollars.\nHe is utilising a weather machine to cause an unending blizzard in NY.\nIf he doesn't get his money on midnight of the Winter solstice he will freeze the city and it inhabitants.\n\nBlanchard's fortress is on an Ice berg off Newfoundland, Canada.\nThe iceberg is secretly above the sunken Titanic (found on 1st of September 1985 in the real world).\nBlanchard and his weather machine are actually in the Titanic, rebuilt as an underwater sea base.\n\nHis iceberg is protected by extreme cold weather.\nThick ice crystals in the frozen sky disable missiles and planes.\nMind controlled cyborg orcas and thick ice protect from sea invasions.\n\n## Military plans\n\nThe USA and [ERA](/History/ERA.qmd) plan to assault the Ice fortress.\nWhilst the main force is distracting the defences this will allow an elite force, including the FIST team, to invade.\n\nFIST will be debriefed on a USA Aircraft carrier.\nThey will be informed of the information in the Sea invasion section.\nThis includes the formation used and what enemies will be present.\nThey will then be tasked with destroying one of the weather spires on the iceberg.\nThis will allow some reinforcement to arrive and also allow the use of Rods from God.\nThey know the main ice fortress is in the centre but do not know what is in it.\n\nEach FIST merc will be provided with the following gear to use during the mission:\n\n- Heated aqua combat suits (1 ARMOR), goes on top of their ground clothing\n- Waterproof backpack allowing storage of 4 items\n- Harpoon gun (1D6+1 DAMAGE)\n\nAdditionally, the FIST team will be provided with 1:\n\n- Rod from God laser targetter (3D6+3, ANTI-MATERIAL), calls down a rod from god. Only works in the air.\n\nWhilst on board FIST can also:\n\n- Enquire about more more intel\n- Give their [CYBORG COLOSSAL SQUIDS](/History/ERA_military.qmd#cyborg_colossal_squid) their 10 word directive.\n- Talk to the leaders of Whale-1 & Whale-2\n\n\n## Sea invasion\n\nThe sea is an uninviting abyss.\nEven with the suits the mercs are frozen to the bone, but they are dry.\nEnemies appear out of nowhere for humans.\nThankfully FIST's steeds do not have this issue.\n\nThe sea invasion consists of an escort mission to the iceberg.\nThey will be attacked by mind controlled Cyborg Orcas and their wranglers.\nReaching the Iceberg is the path to victory.\n\n### Frontal forces\n\nDuring the sea invasion FIST's team will trail behind 2 military groups in the water, Whale-1 & Whale-2.\nThese military groups each consist of 6 marines riding [CYBORG DOLPHINS](/History/USA_military.qmd#cyborg_dolphin), 2 [CYBORG COLOSSAL SQUIDS](/History/ERA_military.qmd#cyborg_colossal_squid), and a [HUMPBACK WHALE SUBMERSIBLE](/History/USA_military.qmd#humpback_sub).\nDo not control directly control these units.\nRather, during the sea invasion, narrate their actions every so often making them succeed and fail in line with the rolls of the FIST characters.\nFor example, if a FIST character rolls a success you can also narrate how the front teams are holding off and killing their enemies.\nIf a FIST character rolls a failure you can narrate and mark the death of members in the front teams.\nOn partial successes the front team may take some losses but also kill some enemies.\n\n### FIST's team\n\nFISTS crew will consists of:\n\n- The FIST mercs\n- A number of [CYBORG DOLPHINS](/History/USA_military.qmd#cyborg_dolphin) equal to 1.5X the number of FIST mercs (rounded down)\n- 2 [CYBORG COLOSSAL SQUIDS](/History/ERA_military.qmd#cyborg_colossal_squid)\n- A [HUMPBACK WHALE SUBMERSIBLE](/History/USA_military.qmd#humpback_sub)\n\n### Blanchard's sea forces\n\nWhilst underwater and approaching the Iceberg the Whale teams will be attacked.\nFIST's team will have to fend off a pod of 6 [CYBORG ORCAS](/Proteus/Blanchard_the_hyperborean.qmd#cyborg_orca) and their [ORCA WRANGLER](/Proteus/Blanchard_the_hyperborean.qmd#orca_wrangler).\nThe frontal forces will be attacked by the same enemies but in larger numbers.\n\n### Victory\n\nThe main goal of FIST is to protect the [HUMPBACK WHALE SUBMERSIBLE](/History/USA_military.qmd#humpback_sub) to the iceberg.\nIt will take 3-6 turns, or however else you measure combat, to reach the iceberg.\nIf FIST are doing well in combat it will take less time than if they are performing poorly.\n\nOnce the Iceberg has been reached the [CYBORG DOLPHINS](/History/USA_military.qmd#cyborg_dolphin) and [HUMPBACK WHALE SUBMERSIBLE](/History/USA_military.qmd#humpback_sub) can climb onto it.\n\n## Ground invasion\n\nEven the dolphins and whales are happy to be out of the sea due to the relative warmth of 0°C air.\nHowever, the dark blue has been replaced by the bright white.\nA flat iceberg surface and still white air disguise the horizon.\n\nThis vision of infinity is slightly broken by the barely visible Ice structures in the distance.\nAs FIST sets up the silence is broken by the sound of fast approaching heavy footsteps.\n\n### Landfall\n\nOnce on land the surviving [HUMPBACK WHALE SUBMERSIBLES](/History/USA_military.qmd#humpback_sub) will deploy into [HUMPBACK WHALE WEAPONS PLATFORM](/History/USA_military.qmd#humpback_plat).\nThis will take a minute or 2 requiring FIST to protect the whale.\nThe mercs will need to remove their Heated aqua combat suits and unpack their gear from their bags.\nIf the other whale teams successfully made it to land this will give more time for FIST's team to set-up before combatants engage them.\n\nThe vanguard of Blanchard's forces will consist of 1D6 [CYBORG POLAR BEAR](#cyborg_polar_bear) with one [POLAR BEAR RIDER](/Proteus/Blanchard_the_hyperborean.qmd#cyborg_polar_bear_rider) each.\n\n### Weather Spire attack\n\nAfter set-up and taking care of the vanguard FIST will need to destroy a weather spire.\nThis will clear a patch of the frozen sky to allow reinforcements to drop in.\nAdditionally, FIST will then be able to use their Rod from God laser targetter.\n\nClose to the weather spire, FIST's team will encounter 8 - X (X is equal to 2 times the number of other whale teams that survived) [CYBORG POLAR BEARS](/Proteus/Blanchard_the_hyperborean.qmd#cyborg_polar_bear) with one [POLAR BEAR RIDER](/Proteus/Blanchard_the_hyperborean.qmd#cyborg_polar_bear_rider) each.\n\nThe weather spire is closely surrounded by 4 defence spires, 1 at each compass point. Each defence spire has 3 [BLANCHARD RIFLEMEN](/Proteus/Blanchard_the_hyperborean.qmd#Blanchard_rifleman) stationed on top of them.\n\n__Weather Spire__ (25HP): A tall tower of ice. At the top of the spire ice is spouting out forming the above frozen sky.\n\n### Weather Spire destruction\n\nOnce the weather spire is deactivated mechas will drop in from the mooners.\nThey will obliterate enemies allowing FIST a clear path to Blanchard's Ice Dome.\n\n## Ice Dome\n\nOnly contains an elevator, a great place for FIST to take a break (rendezvous).\nThe elevator leads down into the sea, it takes a long time going all the way to the Titanic on the sea floor.\n\n## Titanic base\n\nBlanchard and his weather machine are here. He has patch up the Titanic with Ice.\n\n\n\n\n\n\n\n\n\n\n"},"formats":{"html":{"identifier":{"display-name":"HTML","target-format":"html","base-format":"html"},"execute":{"fig-width":7,"fig-height":5,"fig-format":"retina","fig-dpi":96,"df-print":"default","error":false,"eval":true,"cache":null,"freeze":false,"echo":true,"output":true,"warning":true,"include":true,"keep-md":false,"keep-ipynb":false,"ipynb":null,"enabled":null,"daemon":null,"daemon-restart":false,"debug":false,"ipynb-filters":[],"engine":"markdown"},"render":{"keep-tex":false,"keep-source":false,"keep-hidden":false,"prefer-html":false,"output-divs":true,"output-ext":"html","fig-align":"default","fig-pos":null,"fig-env":null,"code-fold":"none","code-overflow":"scroll","code-link":false,"code-line-numbers":false,"code-tools":false,"tbl-colwidths":"auto","merge-includes":true,"inline-includes":false,"preserve-yaml":false,"latex-auto-mk":true,"latex-auto-install":true,"latex-clean":true,"latex-max-runs":10,"latex-makeindex":"makeindex","latex-makeindex-opts":[],"latex-tlmgr-opts":[],"latex-input-paths":[],"latex-output-dir":null,"link-external-icon":false,"link-external-newwindow":false,"self-contained-math":false,"format-resources":[],"notebook-links":true,"format-links":true},"pandoc":{"standalone":true,"wrap":"none","default-image-extension":"png","to":"html","toc":true,"output-file":"M-Blanchards_winter.html"},"language":{"toc-title-document":"Table of contents","toc-title-website":"On this page","related-formats-title":"Other Formats","related-notebooks-title":"Notebooks","source-notebooks-prefix":"Source","section-title-abstract":"Abstract","section-title-appendices":"Appendices","section-title-footnotes":"Footnotes","section-title-references":"References","section-title-reuse":"Reuse","section-title-copyright":"Copyright","section-title-citation":"Citation","appendix-attribution-cite-as":"For attribution, please cite this work as:","appendix-attribution-bibtex":"BibTeX citation:","title-block-author-single":"Author","title-block-author-plural":"Authors","title-block-affiliation-single":"Affiliation","title-block-affiliation-plural":"Affiliations","title-block-published":"Published","title-block-modified":"Modified","callout-tip-title":"Tip","callout-note-title":"Note","callout-warning-title":"Warning","callout-important-title":"Important","callout-caution-title":"Caution","code-summary":"Code","code-tools-menu-caption":"Code","code-tools-show-all-code":"Show All Code","code-tools-hide-all-code":"Hide All Code","code-tools-view-source":"View Source","code-tools-source-code":"Source Code","code-line":"Line","code-lines":"Lines","copy-button-tooltip":"Copy to Clipboard","copy-button-tooltip-success":"Copied!","repo-action-links-edit":"Edit this page","repo-action-links-source":"View source","repo-action-links-issue":"Report an issue","back-to-top":"Back to top","search-no-results-text":"No results","search-matching-documents-text":"matching documents","search-copy-link-title":"Copy link to search","search-hide-matches-text":"Hide additional matches","search-more-match-text":"more match in this document","search-more-matches-text":"more matches in this document","search-clear-button-title":"Clear","search-detached-cancel-button-title":"Cancel","search-submit-button-title":"Submit","search":"Search","toggle-section":"Toggle section","toggle-sidebar":"Toggle sidebar navigation","toggle-dark-mode":"Toggle dark mode","toggle-reader-mode":"Toggle reader mode","toggle-navigation":"Toggle navigation","crossref-fig-title":"Figure","crossref-tbl-title":"Table","crossref-lst-title":"Listing","crossref-thm-title":"Theorem","crossref-lem-title":"Lemma","crossref-cor-title":"Corollary","crossref-prp-title":"Proposition","crossref-cnj-title":"Conjecture","crossref-def-title":"Definition","crossref-exm-title":"Example","crossref-exr-title":"Exercise","crossref-ch-prefix":"Chapter","crossref-apx-prefix":"Appendix","crossref-sec-prefix":"Section","crossref-eq-prefix":"Equation","crossref-lof-title":"List of Figures","crossref-lot-title":"List of Tables","crossref-lol-title":"List of Listings","environment-proof-title":"Proof","environment-remark-title":"Remark","environment-solution-title":"Solution","listing-page-order-by":"Order By","listing-page-order-by-default":"Default","listing-page-order-by-date-asc":"Oldest","listing-page-order-by-date-desc":"Newest","listing-page-order-by-number-desc":"High to Low","listing-page-order-by-number-asc":"Low to High","listing-page-field-date":"Date","listing-page-field-title":"Title","listing-page-field-description":"Description","listing-page-field-author":"Author","listing-page-field-filename":"File Name","listing-page-field-filemodified":"Modified","listing-page-field-subtitle":"Subtitle","listing-page-field-readingtime":"Reading Time","listing-page-field-categories":"Categories","listing-page-minutes-compact":"{0} min","listing-page-category-all":"All","listing-page-no-matches":"No matching items"},"metadata":{"lang":"en","fig-responsive":true,"quarto-version":"1.3.340","editor":{"markdown":{"wrap":"sentence"}},"grid":{"sidebar-width":"200px","body-width":"1000px","margin-width":"200px","gutter-width":"0.75em"},"theme":{"dark":["cyborg","../styles.scss"],"light":["cosmo","../styles.scss"]},"mainfont":"Lexend","title":"Blanchard's Winter"},"extensions":{"book":{"multiFile":true}}}},"projectFormats":["html"]}